vis_game/__init__.py
vis_game/_setup_.py
vis_game/main.py
vis_game/requiment.txt
vis_game/Agent/__init__.py
vis_game/Agent/Numba_KPI/Agent_player.py
vis_game/Agent/Numba_KPI/__init__.py
vis_game/Agent/Trang/Agent_player.py
vis_game/Agent/Trang/__init__.py
vis_game/Agent/player_random/Agent_player.py
vis_game/Agent/player_random/__init__.py
vis_game/base/__init__.py
vis_game/base/Catan/__init__.py
vis_game/base/Catan/basic_action.py
vis_game/base/Catan/env.py
vis_game/base/Catan/index.py
vis_game/base/Catan_v2/Agent.py
vis_game/base/Catan_v2/AgentFunc.py
vis_game/base/Catan_v2/__init__.py
vis_game/base/Catan_v2/env.py
vis_game/base/Catan_v2/relation.py
vis_game/base/Century/CENTURY.xlsx
vis_game/base/Century/__init__.py
vis_game/base/Century/env.py
vis_game/base/MachiKoro/MACHIKORO.xlsx
vis_game/base/MachiKoro/__init__.py
vis_game/base/MachiKoro/env.py
vis_game/base/Sheriff/SHERIFF.xlsx
vis_game/base/Sheriff/__init__.py
vis_game/base/Sheriff/env.py
vis_game/base/Splendor/__init__.py
vis_game/base/Splendor/env.py
vis_game/base/Splendor_v2/Agent_intern.py
vis_game/base/Splendor_v2/__init__.py
vis_game/base/Splendor_v2/env.py
vis_game/base/Splendor_v2/env_intern.py
vis_game/base/SushiGo/__init__.py
vis_game/base/SushiGo/env.py
vis_game/base/TLMN/__init__.py
vis_game/base/TLMN/env.py
vis_game/base/TLMN_v2/__init__.py
vis_game/base/TLMN_v2/env.py
vis_game/system/__init__.py
vis_game/system/mainFunc.py
vis_game/system/Agent/__init__.py
vis_game/system/Agent/An_130922/Agent_player.py
vis_game/system/Agent/An_130922/__init__.py
vis_game/system/Agent/An_130922/Data/__init__.py
vis_game/system/Agent/An_130922/Data/Catan_v2_79200/Ahih1st.npy
vis_game/system/Agent/An_130922/Data/Catan_v2_79200/__init__.py
vis_game/system/Agent/An_130922/Data/SushiGo_79200/Ahih1st.npy
vis_game/system/Agent/An_130922/Data/SushiGo_79200/__init__.py
vis_game/system/Agent/An_200922/Agent_player.py
vis_game/system/Agent/An_200922/__init__.py
vis_game/system/Agent/An_200922/Data/__init__.py
vis_game-0.0.28.dist-info/LICENCE.txt
vis_game-0.0.28.dist-info/METADATA
vis_game-0.0.28.dist-info/WHEEL
vis_game-0.0.28.dist-info/top_level.txt
vis_game-0.0.28.dist-info/RECORD
